privacy/qa/mac/__init__.py
privacy.qa.mac-0.0.1.dist-info/METADATA
privacy.qa.mac-0.0.1.dist-info/WHEEL
privacy.qa.mac-0.0.1.dist-info/top_level.txt
privacy.qa.mac-0.0.1.dist-info/RECORD
